kintsugi_tax_platform_sdk/__init__.py
kintsugi_tax_platform_sdk/_hooks/__init__.py
kintsugi_tax_platform_sdk/_hooks/sdkhooks.py
kintsugi_tax_platform_sdk/_hooks/types.py
kintsugi_tax_platform_sdk/_version.py
kintsugi_tax_platform_sdk/address_validation.py
kintsugi_tax_platform_sdk/addressvalidation.py
kintsugi_tax_platform_sdk/basesdk.py
kintsugi_tax_platform_sdk/customers.py
kintsugi_tax_platform_sdk/errors/__init__.py
kintsugi_tax_platform_sdk/errors/apierror.py
kintsugi_tax_platform_sdk/errors/backend_src_address_validation_responses_validationerrorresponse.py
kintsugi_tax_platform_sdk/errors/backend_src_customers_responses_validationerrorresponse.py
kintsugi_tax_platform_sdk/errors/backend_src_exemptions_responses_validationerrorresponse.py
kintsugi_tax_platform_sdk/errors/backend_src_filings_responses_validationerrorresponse.py
kintsugi_tax_platform_sdk/errors/backend_src_nexus_responses_validationerrorresponse.py
kintsugi_tax_platform_sdk/errors/backend_src_products_responses_validationerrorresponse.py
kintsugi_tax_platform_sdk/errors/backend_src_registrations_responses_validationerrorresponse.py
kintsugi_tax_platform_sdk/errors/backend_src_tax_estimation_responses_validationerrorresponse.py
kintsugi_tax_platform_sdk/errors/backend_src_transactions_responses_validationerrorresponse.py
kintsugi_tax_platform_sdk/errors/errorresponse.py
kintsugi_tax_platform_sdk/errors/httpvalidationerror.py
kintsugi_tax_platform_sdk/errors/no_response_error.py
kintsugi_tax_platform_sdk/errors/responsevalidationerror.py
kintsugi_tax_platform_sdk/errors/sdkerror.py
kintsugi_tax_platform_sdk/exemptions.py
kintsugi_tax_platform_sdk/filings.py
kintsugi_tax_platform_sdk/httpclient.py
kintsugi_tax_platform_sdk/models/__init__.py
kintsugi_tax_platform_sdk/models/addressbase.py
kintsugi_tax_platform_sdk/models/addressresponsedata.py
kintsugi_tax_platform_sdk/models/addresssearchresponse.py
kintsugi_tax_platform_sdk/models/addressstatus.py
kintsugi_tax_platform_sdk-0.10.0.dist-info/METADATA
kintsugi_tax_platform_sdk-0.10.0.dist-info/WHEEL
kintsugi_tax_platform_sdk-0.10.0.dist-info/licenses/LICENSE
kintsugi_tax_platform_sdk-0.10.0.dist-info/RECORD
